app/__init__.py
app/asgi.py
app/settings.py
app/urls.py
app/wsgi.py
customers/__init__.py
customers/admin.py
customers/apps.py
customers/models.py
customers/serializers.py
customers/signals.py
customers/tests.py
customers/urls.py
customers/views.py
customers/migrations/0001_initial.py
customers/migrations/0002_client_dc_tenant_uuid_alter_client_schema_name.py
customers/migrations/0003_alter_client_dc_tenant_uuid.py
customers/migrations/__init__.py
dj_auto_tenant-0.1.2.dist-info/LICENSE
dj_auto_tenant-0.1.2.dist-info/METADATA
dj_auto_tenant-0.1.2.dist-info/WHEEL
dj_auto_tenant-0.1.2.dist-info/top_level.txt
dj_auto_tenant-0.1.2.dist-info/RECORD
