Metadata-Version: 2.1
Name: dj-auto-tenant
Version: 0.1.2
Summary: A small package to create tenants,schemas and domains only by providing a name.
Home-page: https://github.com/krishnababuexp/dj_auto_multitenant
Author: Krishna Bhandari
Author-email: krishnababuexp@gmail.com
Project-URL: Bug Tracker, https://github.com/krishnababuexp/dj_auto_multitenant/sampleproject/issues
Classifier: Programming Language :: Python :: 3
Classifier: License :: OSI Approved :: MIT License
Classifier: Operating System :: OS Independent
Requires-Python: >=3.9
License-File: LICENSE
Requires-Dist: django >=3.2
Requires-Dist: djangorestframework >=3.12.4
Requires-Dist: django-tenants >=3.3.4
